ddev/__init__.py
ddev/__main__.py
ddev/_version.py
ddev/py.typed
ddev/cli/__init__.py
ddev/cli/application.py
ddev/cli/terminal.py
ddev/cli/ci/__init__.py
ddev/cli/ci/codeowners.py
ddev/cli/clean/__init__.py
ddev/cli/config/__init__.py
ddev/cli/config/edit.py
ddev/cli/config/explore.py
ddev/cli/config/find.py
ddev/cli/config/override.py
ddev/cli/config/restore.py
ddev/cli/config/set.py
ddev/cli/config/show.py
ddev/cli/config/update.py
ddev/cli/dep/__init__.py
ddev/cli/dep/common.py
ddev/cli/dep/freeze.py
ddev/cli/dep/pin.py
ddev/cli/dep/sync.py
ddev/cli/dep/updates.py
ddev/cli/docs/__init__.py
ddev/cli/docs/build.py
ddev/cli/docs/serve.py
ddev/cli/env/__init__.py
ddev/cli/env/agent.py
ddev/cli/env/check.py
ddev/cli/env/config.py
ddev/cli/env/reload.py
ddev/cli/env/shell.py
ddev/cli/env/show.py
ddev/cli/env/start.py
ddev/cli/env/stop.py
ddev/cli/env/test.py
ddev/cli/meta/__init__.py
ddev/cli/meta/scripts/__init__.py
ddev/cli/meta/scripts/generate_metrics.py
ddev/cli/meta/scripts/monitor.py
ddev/cli/meta/scripts/saved_views.py
ddev/cli/meta/scripts/serve_openmetrics_payload.py
ddev/cli/meta/scripts/update_py_config.py
ddev/cli/meta/scripts/upgrade_python.py
ddev/cli/meta/scripts/scripts/serve.py
ddev/cli/release/__init__.py
ddev/cli/release/agent/__init__.py
ddev/cli/release/agent/changelog.py
ddev/cli/release/agent/common.py
ddev/cli/release/agent/integrations.py
ddev/cli/release/agent/integrations_changelog.py
ddev/cli/release/branch/__init__.py
ddev/cli/release/branch/create.py
ddev/cli/release/branch/tag.py
ddev/cli/release/changelog/__init__.py
ddev/cli/release/changelog/fix.py
ddev/cli/release/changelog/new.py
ddev/cli/release/list_versions/__init__.py
ddev/cli/release/show/__init__.py
ddev/cli/release/stats/__init__.py
ddev/cli/size/__init__.py
ddev/cli/size/diff.py
ddev/cli/size/historical_metrics.py
ddev/cli/size/status.py
ddev/cli/size/timeline.py
ddev/cli/size/utils/common_funcs.py
ddev/cli/size/utils/common_params.py
ddev/cli/status/__init__.py
ddev-14.1.0.dist-info/METADATA
ddev-14.1.0.dist-info/WHEEL
ddev-14.1.0.dist-info/entry_points.txt
ddev-14.1.0.dist-info/RECORD
