Metadata-Version: 2.4
Name: ddev
Version: 14.1.0
Summary: The Datadog Agent integration developer tool
Project-URL: Source, https://github.com/DataDog/integrations-core
Author-email: Datadog <packages@datadoghq.com>
License-Expression: BSD-3-Clause
Keywords: agent,datadog,integration
Classifier: Development Status :: 5 - Production/Stable
Classifier: Intended Audience :: Developers
Classifier: Intended Audience :: System Administrators
Classifier: License :: OSI Approved :: BSD License
Classifier: Natural Language :: English
Classifier: Operating System :: OS Independent
Classifier: Programming Language :: Python :: 3.13
Requires-Python: >=3.9
Requires-Dist: click~=8.1.6
Requires-Dist: coverage
Requires-Dist: datadog
Requires-Dist: datadog-api-client==2.20.0
Requires-Dist: datadog-checks-dev[cli]<35.6,>=35.5.0
Requires-Dist: hatch>=1.8.1
Requires-Dist: httpx
Requires-Dist: jsonpointer
Requires-Dist: matplotlib
Requires-Dist: pluggy
Requires-Dist: requests
Requires-Dist: rich>=12.5.1
Requires-Dist: squarify
Requires-Dist: stamina==23.2.0
Requires-Dist: tomli-w
Requires-Dist: tomli; python_version < '3.11'
Requires-Dist: tomlkit
Requires-Dist: tqdm
